[
  {
    "hourSalary": 23.3,
    "inEmergency": false,
    "name": "Joaquin",
    "lastName": "Labrador",
    "dateOfBrith": "1998-11-06",
    "id": 41458511,
    "isWorking": false,
    "password": "123gf45",
    "userName": "chefJoaquin"
  },
  {
    "hourSalary": 17.5,
    "name": "Matias",
    "lastName": "Aceval",
    "dateOfBrith": "2001-12-12",
    "id": 43567654,
    "isWorking": false,
    "password": "67sdafdf@-3",
    "userName": "kitchenerMatias"
  },
  {
    "hourSalary": 17.0,
    "inEmergency": false,
    "name": "Maximo",
    "lastName": "Torterolo",
    "dateOfBrith": "2002-06-23",
    "id": 44533543,
    "isWorking": false,
    "password": "34324esds3",
    "userName": "managerMaximo"
  },
  {
    "hourSalary": 15.5,
    "tips": 0.0,
    "name": "Santiago",
    "lastName": "Pavon",
    "dateOfBrith": "2002-04-23",
    "id": 43578956,
    "isWorking": false,
    "password": "23123423Hb2343",
    "userName": "hostSantiago"
  },
  {
    "hourSalary": 17.0,
    "tips": 0.0,
    "name": "Agustin",
    "lastName": "Gomes",
    "dateOfBrith": "1998-09-29",
    "id": 41234234,
    "isWorking": false,
    "password": "@dfd678",
    "userName": "serverAgustin"
  },
  {
    "hourSalary": 17.0,
    "tips": 0.0,
    "name": "Matias",
    "lastName": "Fierro",
    "dateOfBrith": "1996-02-23",
    "id": 39455959,
    "isWorking": false,
    "password": "ebfe@45",
    "userName": "serverMatias"
  }
]